python_page_rank/__init__.py
python_page_rank/cli.py
python_page_rank-0.1.3.dist-info/licenses/LICENSE
python_page_rank-0.1.3.dist-info/METADATA
python_page_rank-0.1.3.dist-info/WHEEL
python_page_rank-0.1.3.dist-info/entry_points.txt
python_page_rank-0.1.3.dist-info/top_level.txt
python_page_rank-0.1.3.dist-info/RECORD
