Metadata-Version: 2.4
Name: python-page-rank
Version: 0.1.3
Summary: Static import graph + PageRank for Python projects
License: MIT License
Keywords: pagerank,static-analysis,imports,dependency-graph
Requires-Python: >=3.9
License-File: LICENSE
Dynamic: license-file
